definable_serializer/LICENSE
definable_serializer/__init__.py
definable_serializer/admin.py
definable_serializer/apps.py
definable_serializer/serializers.py
definable_serializer/views.py
definable_serializer/extra_fields/__init__.py
definable_serializer/models/__init__.py
definable_serializer/models/compat.py
definable_serializer/models/fields.py
definable_serializer/templates/admin/definable_serializer/change_form.html
definable_serializer/templates/admin/definable_serializer/codemirror_script.html
restframework_definable_serializer-0.2.2.dist-info/LICENSE
restframework_definable_serializer-0.2.2.dist-info/METADATA
restframework_definable_serializer-0.2.2.dist-info/WHEEL
restframework_definable_serializer-0.2.2.dist-info/top_level.txt
restframework_definable_serializer-0.2.2.dist-info/RECORD
