Metadata-Version: 2.2
Name: restframework-definable-serializer
Version: 0.2.2
Summary: restframework-definable-serializer
Home-page: https://github.com/salexkidd/restframework-definable-serializer
Author: salexkidd
Author-email: salexkidd@gmail.com
License: MIT
Keywords: django,restframework,serializer
Classifier: Development Status :: 4 - Beta
Classifier: Environment :: Web Environment
Classifier: Framework :: Django
Classifier: Intended Audience :: Developers
Classifier: License :: OSI Approved :: MIT License
Classifier: Operating System :: OS Independent
Classifier: Programming Language :: Python :: 3 :: Only
Classifier: Programming Language :: Python :: 3
Classifier: Programming Language :: Python :: 3.6
Classifier: Topic :: Internet :: WWW/HTTP
Classifier: Topic :: Internet :: WWW/HTTP :: Dynamic Content
License-File: LICENSE
Requires-Dist: django-codemirror2>=0.2
Requires-Dist: jsonfield2>=3.0.3
Requires-Dist: django-yamlfield>=1.0.3
Requires-Dist: PyYAML>=5.2
Requires-Dist: ruamel.yaml>=0.13.5
Requires-Dist: simplejson>=3.11.1
Requires-Dist: six>=1.13.0
Requires-Dist: dateparser>=1.2.0
Dynamic: author
Dynamic: author-email
Dynamic: classifier
Dynamic: description
Dynamic: description-content-type
Dynamic: home-page
Dynamic: keywords
Dynamic: license
Dynamic: requires-dist
Dynamic: summary
